amazing_filters/__init__.py
amazing_filters/filters.py
amazing_filters/image_embed.py
amazing_filters/viewer.py
amazing_filters-1.1.dist-info/METADATA
amazing_filters-1.1.dist-info/WHEEL
amazing_filters-1.1.dist-info/top_level.txt
amazing_filters-1.1.dist-info/RECORD
